isyflask_cli/__init__.py
isyflask_cli/__main__.py
isyflask_cli/cli.py
isyflask_cli/globals.py
isyflask_cli/projects_config/.gitkeep
isyflask_cli/src/docker/__init__.py
isyflask_cli/src/docker/docker.py
isyflask_cli/src/endpoint/__init__.py
isyflask_cli/src/endpoint/endpoint.py
isyflask_cli/src/model/__init__.py
isyflask_cli/src/model/model.py
isyflask_cli/src/project/__init__.py
isyflask_cli/src/project/project.py
isyflask_cli/src/utils/docker.py
isyflask_cli/src/utils/folders.py
isyflask_cli/src/utils/strings.py
isyflask_cli/src/utils/template_gen.py
isyflask_cli-0.6.0.dist-info/METADATA
isyflask_cli-0.6.0.dist-info/WHEEL
isyflask_cli-0.6.0.dist-info/entry_points.txt
isyflask_cli-0.6.0.dist-info/RECORD
