Metadata-Version: 2.1
Name: isyflask-cli
Version: 0.6.0
Summary: Un cli para manejar proyectos de API con flask
Home-page: https://github.com/DavidCuy/easyflask-cli
Author: David Cuy
Author-email: david.cuy.sanchez@gmail.com
Requires-Python: >=3.9,<4.0
Classifier: Programming Language :: Python :: 3
Classifier: Programming Language :: Python :: 3.9
Classifier: Programming Language :: Python :: 3.10
Classifier: Programming Language :: Python :: 3.11
Classifier: Programming Language :: Python :: 3.12
Requires-Dist: PyYAML (>=6.0.1,<6.1.0)
Requires-Dist: cookiecutter (>=2.1.1,<3.0.0)
Requires-Dist: python-dotenv (>=0.20.0,<0.21.0)
Requires-Dist: setuptools (>=72.1.0,<72.2.0)
Requires-Dist: toml (>=0.10.2,<0.11.0)
Requires-Dist: typer[all] (>=0.7.0,<0.8.0)
Requires-Dist: typing-extensions (>=4.9.0,<5.0.0)
Project-URL: Documentation, https://github.com/DavidCuy/easyflask-cli
Project-URL: Repository, https://github.com/DavidCuy/easyflask-cli
